lonadb_client/__init__.py
lonadb_client/lonadb_client.py
lonadb_client-2.3.dist-info/METADATA
lonadb_client-2.3.dist-info/WHEEL
lonadb_client-2.3.dist-info/top_level.txt
lonadb_client-2.3.dist-info/RECORD
