Metadata-Version: 2.1
Name: lonadb-client
Version: 2.3
Summary: A client library for interacting with LonaDB server
Home-page: https://git.lona-development.org/Lona-Development/Clients
Author: Lona-Development
Author-email: collin@lona-development.org
License: MIT
Keywords: lonadb client database
Platform: any
Classifier: Development Status :: 5 - Production/Stable
Classifier: Intended Audience :: Developers
Classifier: License :: OSI Approved :: MIT License
Classifier: Programming Language :: Python :: 3
Classifier: Programming Language :: Python :: 3.6
Classifier: Programming Language :: Python :: 3.7
Classifier: Programming Language :: Python :: 3.8
Classifier: Programming Language :: Python :: 3.9
Requires-Dist: pycryptodome>=3.10.1
